wavencoder/__init__.py
wavencoder/utils.py
wavencoder/layers/__init__.py
wavencoder/layers/attention_layer.py
wavencoder/layers/ftdnn.py
wavencoder/layers/sincnet_layer.py
wavencoder/layers/tdnn.py
wavencoder/models/__init__.py
wavencoder/models/baseline.py
wavencoder/models/lstm_classifier.py
wavencoder/models/rawnet.py
wavencoder/models/sincnet.py
wavencoder/models/wav2vec.py
wavencoder/models/wav2vec2.py
wavencoder/trainer/__init__.py
wavencoder/trainer/classification_trainer.py
wavencoder/transforms/__init__.py
wavencoder/transforms/clip.py
wavencoder/transforms/compose.py
wavencoder/transforms/noise.py
wavencoder/transforms/pad_crop.py
wavencoder/transforms/reverberation.py
wavencoder/transforms/spec_augment.py
wavencoder/transforms/speed.py
wavencoder/transforms/timeshift.py
wavencoder-0.1.3.dist-info/LICENSE
wavencoder-0.1.3.dist-info/METADATA
wavencoder-0.1.3.dist-info/WHEEL
wavencoder-0.1.3.dist-info/top_level.txt
wavencoder-0.1.3.dist-info/RECORD
