Metadata-Version: 2.1
Name: wavencoder
Version: 0.1.3
Summary: WavEncoder - PyTorch backed audio encoder
Home-page: https://github.com/shangeth/wavencoder
Author: Shangeth Rajaa
Author-email: shangethrajaa@gmail.com
License: MIT
Platform: UNKNOWN
Classifier: License :: OSI Approved :: MIT License
Classifier: Programming Language :: Python :: 3
Classifier: Operating System :: OS Independent
Classifier: Topic :: Scientific/Engineering :: Artificial Intelligence
Classifier: Intended Audience :: Developers
Classifier: Intended Audience :: Education
Classifier: Intended Audience :: Science/Research
Requires-Python: >=3.6
Requires-Dist: numpy (>=1.19.2)
Requires-Dist: torch (>=1.6.0)
Requires-Dist: torchaudio (>=0.6.0)
Requires-Dist: tqdm
Requires-Dist: fairseq
